databind/__init__.py
databind/yaml/__init__.py
databind/yaml/py.typed
databind/yaml/test_yaml.py
databind.yaml-0.1.3.dist-info/LICENSE.txt
databind.yaml-0.1.3.dist-info/METADATA
databind.yaml-0.1.3.dist-info/WHEEL
databind.yaml-0.1.3.dist-info/top_level.txt
databind.yaml-0.1.3.dist-info/RECORD
