Metadata-Version: 2.1
Name: databind.yaml
Version: 0.1.3
Summary: De/serialize YAML payloads using Python type hints.
Home-page: https://github.com/NiklasRosenstein/python-databind
Author: Niklas Rosenstein
Author-email: rosensteinniklas@gmail.com
License: MIT
Platform: UNKNOWN
Requires-Python: >=3.5.0,<4.0.0
Requires-Dist: databind.core (<1.0.0,>=0.1.0)
Requires-Dist: databind.json (<1.0.0,>=0.1.0)
Requires-Dist: PyYAML (<6.0.0,>=5.0.0)
